ionizer/__init__.py
ionizer/decompositions.py
ionizer/identity_hunter.py
ionizer/ops.py
ionizer/resources/__init__.py
ionizer/resources/double_gate_identities.pkl
ionizer/resources/triple_gate_identities.pkl
ionizer/transforms.py
ionizer/utils.py
ionizer-0.3.0.dist-info/LICENSE
ionizer-0.3.0.dist-info/METADATA
ionizer-0.3.0.dist-info/WHEEL
ionizer-0.3.0.dist-info/RECORD
