Metadata-Version: 2.1
Name: ionizer
Version: 0.3.0
Summary: PennyLane tools for compilation into trapped-ion native gates.
Home-page: https://github.com/QSAR-UBC/ionizer/
License: MIT
Keywords: quantum-computing,quantum-software
Author: UBC Quantum Software and Algorithms Research Lab
Requires-Python: >=3.10,<4.0
Classifier: License :: OSI Approved :: MIT License
Classifier: Programming Language :: Python :: 3
Classifier: Programming Language :: Python :: 3.10
Classifier: Programming Language :: Python :: 3.11
Classifier: Programming Language :: Python :: 3.12
Requires-Dist: pennylane (>=0.37,<0.38)
Project-URL: Repository, https://github.com/QSAR-UBC/ionizer/
